LICENSE.txt
README.md
pyproject.toml
seqsearch/__init__.py
seqsearch.egg-info/PKG-INFO
seqsearch.egg-info/SOURCES.txt
seqsearch.egg-info/dependency_links.txt
seqsearch.egg-info/requires.txt
seqsearch.egg-info/top_level.txt
seqsearch/databases/__init__.py
seqsearch/databases/human.py
seqsearch/databases/humgut.py
seqsearch/databases/ncbi_16s.py
seqsearch/databases/nr.py
seqsearch/databases/nt.py
seqsearch/databases/pfam.py
seqsearch/databases/pr_two.py
seqsearch/databases/refseq.py
seqsearch/databases/silva.py
seqsearch/databases/string.py
seqsearch/databases/tigrfam.py
seqsearch/databases/mothur/greengenes.py
seqsearch/databases/mothur/rdp.py
seqsearch/databases/mothur/silva.py
seqsearch/examples/download.py
seqsearch/examples/blast_object/simple_blast.py
seqsearch/examples/seqsearch_object/simple_query.py
seqsearch/mapping/bam.py
seqsearch/mapping/bam_and_sam.py
seqsearch/mapping/bwa.py
seqsearch/mapping/sam.py
seqsearch/search/__init__.py
seqsearch/search/blast.py
seqsearch/search/core.py
seqsearch/search/hmmer.py
seqsearch/search/parallel.py
seqsearch/search/vsearch.py