Metadata-Version: 2.4
Name: seqsearch
Version: 2.2.2
Summary: Sequence similarity searches (e.g. BLAST) made easy.
Author-email: Lucas Sinclair <lucas.sinclair@me.com>
License: Copyright (c) 2026 Lucas Sinclair
Project-URL: Homepage, https://github.com/xapple/seqsearch
Keywords: bioinformatics,dna,sequences,search
Classifier: License :: OSI Approved :: MIT License
Classifier: Operating System :: OS Independent
Classifier: Topic :: Scientific/Engineering :: Bio-Informatics
Requires-Python: >=3.8
License-File: LICENSE.txt
Requires-Dist: autopaths>=1.6.2
Requires-Dist: plumbing>=2.11.3
Requires-Dist: fasta>=2.3.3
Requires-Dist: biopython
Requires-Dist: sh
Requires-Dist: tqdm
Provides-Extra: ftp
Requires-Dist: ftputil; extra == "ftp"
Provides-Extra: downloads
Requires-Dist: wget; extra == "downloads"
Dynamic: license-file
